robohatlib/.idea/.gitignore
robohatlib/.idea/inspectionProfiles/profiles_settings.xml
robohatlib/.idea/misc.xml
robohatlib/.idea/modules.xml
robohatlib/.idea/robohatlib.iml
robohatlib/Robohat.py
robohatlib/RobohatConfig.py
robohatlib/RobohatConstants.py
robohatlib/__init__.py
robohatlib/driver_ll/GPI_LL_Driver.py
robohatlib/driver_ll/GPI_LL_Interrupt.py
robohatlib/driver_ll/GPOPWM_LL_Driver.py
robohatlib/driver_ll/GPO_LL_Driver.py
robohatlib/driver_ll/IOHandler.py
robohatlib/driver_ll/__init__.py
robohatlib/driver_ll/constants/GPOStat.py
robohatlib/driver_ll/constants/GpioDirection.py
robohatlib/driver_ll/constants/InterruptTypes.py
robohatlib/driver_ll/constants/__init__.py
robohatlib/driver_ll/datastructs/IOStatus.py
robohatlib/driver_ll/datastructs/__init__.py
robohatlib/driver_ll/definitions/GPIDef.py
robohatlib/driver_ll/definitions/GPIInterruptDef.py
robohatlib/driver_ll/definitions/GPODef.py
robohatlib/driver_ll/definitions/GPOPWMDef.py
robohatlib/driver_ll/definitions/IOExpanderDef.py
robohatlib/driver_ll/definitions/InterruptCallbackHolder.py
robohatlib/driver_ll/definitions/LedDef.py
robohatlib/driver_ll/definitions/MCPInterruptDef.py
robohatlib/driver_ll/definitions/MultiColorLedDef.py
robohatlib/driver_ll/definitions/SerialDef.py
robohatlib/driver_ll/definitions/__init__.py
robohatlib/driver_ll/i2c/I2CBus.py
robohatlib/driver_ll/i2c/I2CBusDef.py
robohatlib/driver_ll/i2c/I2CDevice.py
robohatlib/driver_ll/i2c/I2CDeviceDef.py
robohatlib/driver_ll/i2c/I2CHandler.py
robohatlib/driver_ll/i2c/__init__.py
robohatlib/driver_ll/i2c/smbus.py
robohatlib/driver_ll/spi/SPIBusDef.py
robohatlib/driver_ll/spi/SPIDevice.py
robohatlib/driver_ll/spi/SPIDeviceDef.py
robohatlib/driver_ll/spi/__init__.py
robohatlib/drivers/BuzzerDriver.py
robohatlib/drivers/LIS3MDL.py
robohatlib/drivers/LSM6DS33.py
robohatlib/drivers/LedDriver.py
robohatlib/drivers/MAX11137.py
robohatlib/drivers/MAX11607.py
robohatlib/drivers/MCP23008.py
robohatlib/drivers/PCA9685.py
revolve2_robohat-0.6.3.dist-info/METADATA
revolve2_robohat-0.6.3.dist-info/WHEEL
revolve2_robohat-0.6.3.dist-info/RECORD
