Metadata-Version: 2.1
Name: revolve2-robohat
Version: 0.6.3
Summary: Robohatlib
Home-page: https://github.com/ci-group/robohat
Author: Arnoud Denker
Author-email: a.denker@vu.nl
Requires-Python: >=3.9,<4.0
Classifier: Development Status :: 4 - Beta
Classifier: Programming Language :: Python :: 3
Classifier: Programming Language :: Python :: 3.9
Classifier: Programming Language :: Python :: 3.10
Classifier: Programming Language :: Python :: 3.11
Classifier: Programming Language :: Python :: 3.12
Classifier: Programming Language :: Python :: 3.13
Classifier: Typing :: Typed
Provides-Extra: dev
Requires-Dist: RPi.GPIO (>=0.7.1,<0.8.0)
Requires-Dist: spidev (>=3.6,<4.0)
Project-URL: Repository, https://github.com/ci-group/robohat
